pangoline/cli.py
pangoline/rasterize.py
pangoline/render.py
pangoline/templates/alto.tmpl
pangoline_tool-0.3.0.dist-info/licenses/AUTHORS
pangoline_tool-0.3.0.dist-info/licenses/LICENSE
pangoline_tool-0.3.0.dist-info/METADATA
pangoline_tool-0.3.0.dist-info/WHEEL
pangoline_tool-0.3.0.dist-info/entry_points.txt
pangoline_tool-0.3.0.dist-info/pbr.json
pangoline_tool-0.3.0.dist-info/top_level.txt
pangoline_tool-0.3.0.dist-info/RECORD
