Metadata-Version: 2.4
Name: pangoline-tool
Version: 0.3.0
Summary: Synthetic document rendering with parallel ALTO output
Home-page: http://pangoline.github.io
Author: Benjamin Kiessling
Author-email: mittagessen@l.unchti.me
License: Apache-2.0
Keywords: atr,document rendering,alto
Classifier: Environment :: Console
Classifier: Intended Audience :: Science/Research
Classifier: Operating System :: POSIX
Classifier: Programming Language :: Python :: 3.9
Classifier: Programming Language :: Python :: 3.10
Classifier: Programming Language :: Python :: 3.11
Classifier: Programming Language :: Python :: 3.12
Classifier: Programming Language :: Python :: 3.13
Requires-Python: >=3.9
License-File: LICENSE
License-File: AUTHORS
Requires-Dist: click
Requires-Dist: rich
Requires-Dist: jinja2
Requires-Dist: PyGObject
Requires-Dist: pypdfium2
Requires-Dist: lxml
Requires-Dist: pillow
Requires-Dist: numpy
Requires-Dist: regex
Dynamic: author
Dynamic: author-email
Dynamic: classifier
Dynamic: home-page
Dynamic: keywords
Dynamic: license
Dynamic: license-file
Dynamic: summary
